{
    "0": "Reason type: [2]",
    "1": "Reason type: [2]",
    "2": "Reason type: [2]",
    "3": "Non-responsive Error",
    "4": "Reason type: [2]",
    "5": "Reason type: [2]",
    "6": "Reason type: [2]",
    "7": "Reason type: [2]",
    "9": "Non-responsive Error",
    "10": "Reason type: [2]",
    "11": "Reason type: [2]",
    "13": "Reason type: [2]",
    "17": "Reason type: [2]",
    "18": "Reason type: [2]",
    "20": "Reason type: [2]",
    "21": "Non-responsive Error",
    "23": "Reason type: [2]",
    "24": "Reason type: [2]",
    "26": "Reason type: [2]",
    "27": "Reason type: [2]",
    "29": "Reason type: [2]",
    "30": "Reason type: [2]",
    "31": "Reason type: [2]",
    "33": "Reason type: [2]",
    "34": "Non-responsive Error",
    "35": "Reason type: [2]",
    "37": "Reason type: [2]",
    "38": "Reason type: [2]",
    "39": "Reason type: [2]",
    "40": "Reason type: [2]",
    "41": "Reason type: [2]",
    "42": "Reason type: [2]",
    "43": "Reason type: [2]",
    "44": "Reason type: [2]",
    "45": "Non-responsive Error",
    "46": "Reason type: [2]",
    "48": "Reason type: [2]",
    "49": "Reason type: [2]",
    "50": "Reason type: [2]",
    "51": "Reason type: [2]",
    "52": "Non-responsive Error",
    "53": "Non-responsive Error",
    "55": "Reason type: [2]",
    "56": "Reason type: [2]",
    "57": "Non-responsive Error",
    "58": "Reason type: [2]",
    "59": "Reason type: [2]",
    "60": "Reason type: [2]",
    "62": "Reason type: [2]",
    "64": "Reason type: [2]",
    "65": "Non-responsive Error",
    "67": "Reason type: [2]",
    "68": "Non-responsive Error",
    "70": "Reason type: [2]",
    "71": "Reason type: [2]",
    "72": "Non-responsive Error",
    "73": "Reason type: [2]",
    "74": "Reason type: [2]",
    "75": "Reason type: [2]",
    "76": "Reason type: [2]",
    "77": "Reason type: [2]",
    "78": "Reason type: [2]",
    "80": "Reason type: [2]",
    "81": "Reason type: [2]",
    "82": "Reason type: [2]",
    "83": "Non-responsive Error",
    "84": "Reason type: [2]",
    "85": "Reason type: [2]",
    "86": "Reason type: [2]",
    "87": "Reason type: [2]",
    "89": "Reason type: [2]",
    "90": "Reason type: [2]",
    "91": "Reason type: [2]",
    "92": "Non-responsive Error",
    "94": "Reason type: [2]",
    "95": "Reason type: [2]",
    "96": "Reason type: [2]",
    "97": "Reason type: [2]",
    "99": "Reason type: [2]",
    "102": "Reason type: [2]",
    "103": "Reason type: [2]",
    "106": "Reason type: [2]",
    "107": "Reason type: [2]",
    "108": "Reason type: [2]",
    "109": "Reason type: [2]",
    "110": "Non-responsive Error",
    "111": "Reason type: [2]",
    "112": "Non-responsive Error",
    "113": "Reason type: [2]",
    "114": "Non-responsive Error",
    "115": "Reason type: [2]",
    "117": "Reason type: [2]",
    "118": "Reason type: [2]",
    "120": "Reason type: [2]",
    "123": "Reason type: [2]",
    "126": "Non-responsive Error",
    "127": "Reason type: [2]",
    "128": "Reason type: [2]",
    "129": "Reason type: [2]",
    "130": "Reason type: [2]",
    "133": "Reason type: [2]",
    "134": "Non-responsive Error",
    "135": "Reason type: [2]",
    "136": "Reason type: [2]",
    "137": "Reason type: [2]",
    "138": "Reason type: [2]",
    "140": "Reason type: [2]",
    "142": "Reason type: [2]",
    "143": "Reason type: [2]",
    "144": "Reason type: [2]",
    "145": "Reason type: [2]",
    "146": "Reason type: [2]",
    "147": "Non-responsive Error",
    "150": "Reason type: [2]",
    "152": "Reason type: [2]",
    "153": "Reason type: [2]",
    "155": "Non-responsive Error",
    "157": "Reason type: [2]",
    "158": "Non-responsive Error",
    "159": "Non-responsive Error",
    "161": "Reason type: [2]",
    "163": "Reason type: [2]",
    "164": "Reason type: [2]",
    "165": "Reason type: [2]",
    "166": "Reason type: [2]",
    "167": "Reason type: [2]",
    "169": "Reason type: [2]",
    "170": "Non-responsive Error",
    "172": "Reason type: [2]",
    "173": "Reason type: [2]",
    "174": "Reason type: [2]",
    "175": "Reason type: [2]",
    "176": "Reason type: [2]",
    "177": "Non-responsive Error",
    "178": "Reason type: [2]",
    "179": "Reason type: [2]",
    "180": "Reason type: [2]",
    "183": "Non-responsive Error",
    "184": "Non-responsive Error",
    "186": "Non-responsive Error",
    "188": "Non-responsive Error",
    "189": "Reason type: [2]",
    "190": "Non-responsive Error",
    "191": "Non-responsive Error",
    "193": "Reason type: [2]",
    "195": "Reason type: [2]",
    "197": "Reason type: [2]",
    "198": "Non-responsive Error",
    "199": "Reason type: [2]",
    "200": "Reason type: [2]",
    "204": "Reason type: [2]",
    "205": "Reason type: [2]",
    "207": "Reason type: [2]",
    "208": "Reason type: [2]",
    "209": "Reason type: [2]",
    "211": "Non-responsive Error",
    "212": "Reason type: [2]",
    "213": "Reason type: [2]",
    "214": "Non-responsive Error",
    "216": "Reason type: [2]",
    "218": "Non-responsive Error",
    "219": "Non-responsive Error",
    "220": "Reason type: [2]",
    "222": "Non-responsive Error",
    "223": "Reason type: [2]",
    "225": "Non-responsive Error",
    "226": "Non-responsive Error",
    "227": "Reason type: [2]",
    "228": "Reason type: [2]",
    "229": "Reason type: [2]",
    "230": "Reason type: [2]",
    "232": "Reason type: [2]",
    "233": "Reason type: [2]",
    "234": "Reason type: [2]",
    "235": "Non-responsive Error",
    "236": "Reason type: [2]",
    "237": "Reason type: [2]",
    "238": "Reason type: [2]",
    "239": "Reason type: [2]",
    "240": "Reason type: [2]",
    "242": "Reason type: [2]",
    "246": "Reason type: [2]",
    "248": "Reason type: [2]",
    "249": "Reason type: [2]",
    "250": "Reason type: [2]",
    "251": "Reason type: [2]",
    "253": "Reason type: [2]",
    "256": "Reason type: [2]",
    "257": "Reason type: [2]",
    "259": "Reason type: [2]",
    "260": "Reason type: [2]",
    "261": "Reason type: [2]",
    "262": "Non-responsive Error",
    "263": "Reason type: [2]",
    "264": "Non-responsive Error",
    "265": "Reason type: [2]",
    "266": "Reason type: [2]",
    "267": "Reason type: [2]",
    "268": "Reason type: [2]",
    "269": "Reason type: [2]",
    "270": "Reason type: [2]",
    "271": "Reason type: [2]",
    "272": "Non-responsive Error",
    "274": "Reason type: [2]",
    "275": "Non-responsive Error",
    "278": "Reason type: [2]",
    "281": "Reason type: [2]",
    "282": "Reason type: [2]",
    "283": "Reason type: [2]",
    "284": "Reason type: [2]",
    "285": "Reason type: [2]",
    "286": "Non-responsive Error",
    "288": "Reason type: [2]",
    "289": "Reason type: [2]",
    "290": "Reason type: [2]",
    "291": "Non-responsive Error",
    "294": "Reason type: [2]",
    "295": "Reason type: [2]",
    "297": "Reason type: [2]",
    "298": "Reason type: [2]",
    "299": "Reason type: [2]",
    "300": "Reason type: [2]",
    "302": "Reason type: [2]",
    "304": "Reason type: [2]",
    "305": "Reason type: [2]",
    "307": "Reason type: [2]",
    "309": "Reason type: [2]",
    "310": "Reason type: [2]",
    "311": "Reason type: [2]",
    "312": "Reason type: [2]",
    "313": "Reason type: [2]",
    "314": "Reason type: [2]",
    "315": "Reason type: [2]",
    "316": "Reason type: [2]",
    "318": "Non-responsive Error",
    "319": "Reason type: [2]",
    "321": "Reason type: [2]",
    "323": "Reason type: [2]",
    "324": "Reason type: [2]",
    "326": "Reason type: [2]",
    "327": "Reason type: [2]",
    "328": "Non-responsive Error",
    "330": "Non-responsive Error",
    "331": "Non-responsive Error",
    "332": "Non-responsive Error",
    "333": "Reason type: [2]",
    "334": "Reason type: [2]",
    "335": "Non-responsive Error",
    "337": "Reason type: [2]",
    "339": "Reason type: [2]",
    "340": "Reason type: [2]",
    "341": "Non-responsive Error",
    "342": "Reason type: [2]",
    "343": "Reason type: [2]",
    "345": "Non-responsive Error",
    "346": "Reason type: [2]",
    "349": "Non-responsive Error",
    "350": "Non-responsive Error",
    "351": "Reason type: [2]",
    "352": "Reason type: [2]",
    "353": "Reason type: [2]",
    "354": "Reason type: [2]",
    "355": "Non-responsive Error",
    "356": "Non-responsive Error",
    "357": "Reason type: [2]",
    "359": "Reason type: [2]",
    "361": "Reason type: [2]",
    "362": "Reason type: [2]",
    "364": "Reason type: [2]",
    "365": "Non-responsive Error",
    "366": "Non-responsive Error",
    "367": "Non-responsive Error",
    "370": "Reason type: [2]",
    "371": "Reason type: [2]",
    "372": "Reason type: [2]",
    "374": "Non-responsive Error",
    "375": "Reason type: [2]",
    "377": "Non-responsive Error",
    "379": "Non-responsive Error",
    "380": "Reason type: [2]",
    "381": "Reason type: [2]",
    "382": "Reason type: [2]",
    "383": "Reason type: [2]",
    "384": "Non-responsive Error",
    "385": "Reason type: [2]",
    "386": "Non-responsive Error",
    "387": "Reason type: [2]",
    "389": "Reason type: [2]",
    "391": "Reason type: [2]",
    "393": "Reason type: [2]",
    "395": "Non-responsive Error",
    "397": "Reason type: [2]",
    "398": "Reason type: [2]",
    "401": "Reason type: [2]",
    "403": "Reason type: [2]",
    "404": "Reason type: [2]",
    "405": "Reason type: [2]",
    "406": "Non-responsive Error",
    "407": "Reason type: [2]",
    "408": "Non-responsive Error",
    "409": "Reason type: [2]",
    "410": "Reason type: [2]",
    "412": "Reason type: [2]",
    "415": "Non-responsive Error",
    "416": "Reason type: [2]",
    "417": "Non-responsive Error",
    "418": "Reason type: [2]",
    "419": "Reason type: [2]",
    "420": "Reason type: [2]",
    "421": "Non-responsive Error",
    "422": "Reason type: [2]",
    "423": "Reason type: [2]",
    "424": "Reason type: [2]",
    "426": "Reason type: [2]",
    "427": "Reason type: [2]",
    "428": "Non-responsive Error",
    "429": "Reason type: [2]",
    "430": "Non-responsive Error",
    "432": "Reason type: [2]",
    "434": "Reason type: [2]",
    "436": "Reason type: [2]",
    "437": "Reason type: [2]",
    "438": "Reason type: [2]",
    "439": "Reason type: [2]",
    "440": "Reason type: [2]",
    "441": "Non-responsive Error",
    "444": "Reason type: [2]",
    "445": "Reason type: [2]",
    "446": "Reason type: [2]",
    "448": "Reason type: [2]",
    "449": "Non-responsive Error",
    "450": "Reason type: [2]",
    "451": "Reason type: [2]",
    "452": "Non-responsive Error",
    "453": "Reason type: [2]",
    "454": "Reason type: [2]",
    "455": "Reason type: [2]",
    "456": "Reason type: [2]",
    "458": "Reason type: [2]",
    "459": "Reason type: [2]",
    "460": "Reason type: [2]",
    "462": "Reason type: [2]",
    "463": "Reason type: [2]",
    "464": "Reason type: [2]",
    "465": "Reason type: [2]",
    "467": "Non-responsive Error",
    "468": "Reason type: [2]",
    "469": "Non-responsive Error",
    "470": "Reason type: [2]",
    "471": "Non-responsive Error",
    "472": "Non-responsive Error",
    "474": "Reason type: [2]",
    "475": "Reason type: [2]",
    "476": "Non-responsive Error",
    "477": "Reason type: [2]",
    "478": "Reason type: [2]",
    "480": "Reason type: [2]",
    "481": "Reason type: [2]",
    "482": "Reason type: [2]",
    "484": "Reason type: [2]",
    "485": "Reason type: [2]",
    "486": "Reason type: [2]",
    "487": "Reason type: [2]",
    "488": "Reason type: [2]",
    "489": "Reason type: [2]",
    "490": "Reason type: [2]",
    "491": "Reason type: [2]",
    "492": "Reason type: [2]",
    "494": "Reason type: [2]",
    "495": "Reason type: [2]",
    "496": "Reason type: [2]",
    "497": "Non-responsive Error",
    "498": "Reason type: [2]",
    "500": "Reason type: [2]",
    "501": "Reason type: [2]",
    "503": "Reason type: [2]",
    "504": "Reason type: [2]",
    "505": "Reason type: [2]",
    "506": "Reason type: [2]",
    "508": "Reason type: [2]",
    "509": "Reason type: [2]",
    "511": "Reason type: [2]",
    "513": "Reason type: [2]",
    "514": "Reason type: [2]",
    "515": "Reason type: [2]",
    "517": "Reason type: [2]",
    "518": "Reason type: [2]",
    "521": "Reason type: [2]",
    "522": "Reason type: [2]",
    "523": "Reason type: [2]",
    "525": "Reason type: [2]",
    "527": "Non-responsive Error",
    "528": "Reason type: [2]",
    "529": "Reason type: [2]",
    "530": "Reason type: [2]",
    "536": "Reason type: [2]",
    "538": "Reason type: [2]",
    "542": "Reason type: [2]",
    "545": "Reason type: [2]",
    "546": "Reason type: [2]",
    "549": "Reason type: [2]",
    "550": "Reason type: [2]",
    "552": "Reason type: [2]",
    "553": "Reason type: [2]",
    "555": "Reason type: [2]",
    "556": "Reason type: [2]",
    "558": "Reason type: [2]",
    "559": "Reason type: [2]",
    "560": "Reason type: [2]",
    "562": "Reason type: [2]",
    "563": "Reason type: [2]",
    "564": "Reason type: [2]",
    "565": "Reason type: [2]",
    "566": "Reason type: [2]",
    "567": "Reason type: [2]",
    "568": "Reason type: [2]",
    "569": "Reason type: [2]",
    "570": "Reason type: [2]",
    "571": "Non-responsive Error",
    "572": "Non-responsive Error",
    "573": "Reason type: [2]",
    "574": "Reason type: [2]",
    "575": "Reason type: [2]",
    "576": "Reason type: [2]",
    "577": "Reason type: [2]",
    "578": "Reason type: [2]",
    "579": "Reason type: [2]",
    "580": "Reason type: [2]",
    "581": "Reason type: [2]",
    "582": "Reason type: [2]",
    "583": "Reason type: [2]",
    "584": "Non-responsive Error",
    "585": "Reason type: [2]",
    "586": "Reason type: [2]",
    "587": "Reason type: [2]",
    "588": "Reason type: [2]",
    "589": "Reason type: [2]",
    "590": "Reason type: [2]",
    "591": "Reason type: [2]",
    "592": "Reason type: [2]",
    "593": "Reason type: [2]",
    "594": "Reason type: [2]",
    "595": "Non-responsive Error",
    "597": "Reason type: [2]",
    "598": "Reason type: [2]",
    "599": "Reason type: [2]",
    "600": "Reason type: [2]"
}